Metadata-Version: 1.0
Name: kg100-distributions
Version: 0.1
Summary: Gaussian and Binomial distributions
Home-page: UNKNOWN
Author: Krishna Goel
Author-email: kgoel100@gmail.com
License: UNKNOWN
Platform: UNKNOWN
